piggypandas/__init__.py
piggypandas/_version.py
piggypandas/argparseutils.py
piggypandas/cleanup.py
piggypandas/credentials.py
piggypandas/dfutils.py
piggypandas/fileinput.py
piggypandas/fileoutput.py
piggypandas/mapper.py
piggypandas/mdxinput.py
piggypandas/progress.py
piggypandas/scriptutils.py
piggypandas/styler.py
piggypandas/types.py
piggypandas-2.0.9.dist-info/LICENSE
piggypandas-2.0.9.dist-info/METADATA
piggypandas-2.0.9.dist-info/WHEEL
piggypandas-2.0.9.dist-info/top_level.txt
piggypandas-2.0.9.dist-info/RECORD
