Metadata-Version: 2.1
Name: piggypandas
Version: 2.0.9
Summary: A few helpers for more efficient pandas work
Home-page: https://github.com/dstillermann/piggypandas
Author: Dmitry Stillermannm
Author-email: dmitry@stillermann.com
Classifier: Programming Language :: Python :: 3
Classifier: License :: CC0 1.0 Universal (CC0 1.0) Public Domain Dedication
Classifier: Operating System :: OS Independent
Classifier: Development Status :: 3 - Alpha
Classifier: Intended Audience :: Developers
Classifier: Topic :: Software Development :: Libraries :: Python Modules
Requires-Python: >=3.9
License-File: LICENSE
Requires-Dist: build
Requires-Dist: numpy
Requires-Dist: pandas >=2.1.0
Requires-Dist: pywin32
Requires-Dist: setuptools
Requires-Dist: twine
Requires-Dist: xlsxwriter
Requires-Dist: openpyxl
